LICENSE
MANIFEST.in
README.md
setup.py
Zeras/__init__.py
Zeras/data_batcher.py
Zeras/data_parallelism.py
Zeras/model_baseboard.py
Zeras/model_settings_baseboard.py
Zeras/model_template.py
Zeras/optim.py
Zeras/test.py
Zeras/vocab.py
Zeras/zoo_layers.py
Zeras/zoo_nn.py
Zeras.egg-info/PKG-INFO
Zeras.egg-info/SOURCES.txt
Zeras.egg-info/dependency_links.txt
Zeras.egg-info/top_level.txt