Metadata-Version: 2.1
Name: Zeras
Version: 0.4.4
Summary: A package of deep-learning utilities.
Home-page: https://github.com/Li-Ming-Fan/Zeras
Author: Ming-Fan Li
Author-email: li_m_f@163.com
Maintainer: Ming-Fan Li
Maintainer-email: li_m_f@163.com
License: UNKNOWN
Platform: any
